EnumEnvVars.py
EnumImages.py
EnumSecrets.py
docker_enumsensitive-0.1.7.dist-info/METADATA
docker_enumsensitive-0.1.7.dist-info/WHEEL
docker_enumsensitive-0.1.7.dist-info/entry_points.txt
docker_enumsensitive-0.1.7.dist-info/top_level.txt
docker_enumsensitive-0.1.7.dist-info/RECORD
