Metadata-Version: 2.4
Name: docker-enumsensitive
Version: 0.1.7
Summary: Docker Engine HTTP API enumeration helpers for env vars, secrets, and images.
Author-email: Defensive Origins <info@defensiveorigins.com>
License: MIT
Project-URL: Homepage, https://github.com/DefensiveOrigins/DockerEngineAPI-EnumSensitive
Project-URL: Source, https://github.com/DefensiveOrigins/DockerEngineAPI-EnumSensitive
Project-URL: Issues, https://github.com/DefensiveOrigins/DockerEngineAPI-EnumSensitive/issues
Keywords: docker,security,enumeration,api,pentest,red-team
Classifier: Development Status :: 3 - Alpha
Classifier: Intended Audience :: Information Technology
Classifier: Intended Audience :: System Administrators
Classifier: Intended Audience :: Developers
Classifier: Topic :: Security
Classifier: Topic :: System :: Systems Administration
Classifier: License :: OSI Approved :: MIT License
Classifier: Programming Language :: Python
Classifier: Programming Language :: Python :: 3
Classifier: Programming Language :: Python :: 3.8
Classifier: Programming Language :: Python :: 3.9
Classifier: Programming Language :: Python :: 3.10
Classifier: Programming Language :: Python :: 3.11
Classifier: Programming Language :: Python :: 3.12
Classifier: Environment :: Console
Classifier: Operating System :: OS Independent
Requires-Python: >=3.8
Requires-Dist: requests
Requires-Dist: alive-progress
